README.rst
setup.py
bypass_js/__init__.py
bypass_js.egg-info/PKG-INFO
bypass_js.egg-info/SOURCES.txt
bypass_js.egg-info/dependency_links.txt
bypass_js.egg-info/not-zip-safe
bypass_js.egg-info/top_level.txt