Metadata-Version: 1.1
Name: bypass-js
Version: 0.0.1
Summary: Package description
